{"version":2,"kind":"Notebook","sha256":"7fcf56087bdc00d51f4e0caf8c6bb37eecf0a0e06f5bfd3f0e45cfe798c8e591","slug":"notebooks.example-workflows.cneos-fireball","location":"/notebooks/example-workflows/cneos-fireball.ipynb","dependencies":[],"frontmatter":{"title":"NASA API: World Map of Fireball Impacts","content_includes_title":true,"kernelspec":{"name":"python3","display_name":"Python 3 (ipykernel)","language":"python"},"authors":[{"nameParsed":{"literal":"Project Pythia Community","given":"Project Pythia","family":"Community"},"name":"Project Pythia Community","url":"https://projectpythia.org/","id":"contributors-myst-generated-uid-0"}],"open_access":true,"license":{"content":{"id":"CC-BY-4.0","url":"https://creativecommons.org/licenses/by/4.0/","name":"Creative Commons Attribution 4.0 International","free":true,"CC":true},"code":{"id":"Apache-2.0","url":"https://opensource.org/licenses/Apache-2.0","name":"Apache License 2.0","free":true,"osi":true}},"github":"https://github.com/projectpythia/api-cookbook","copyright":"2024","affiliations":[{"id":"UAlbany","name":"University at Albany (SUNY)","department":"Atmospheric and Environmental Sciences","url":"https://www.albany.edu/daes"},{"id":"CISL","name":"NSF National Center for Atmospheric Research","department":"Computational and Information Systems Lab","url":"https://www.cisl.ucar.edu"},{"id":"Unidata","name":"NSF Unidata","url":"https://www.unidata.ucar.edu"},{"id":"Argonne","name":"Argonne National Laboratory","department":"Environmental Science Division","url":"https://www.anl.gov/evs"},{"id":"CarbonPlan","name":"CarbonPlan","url":"https://carbonplan.org"},{"id":"NVIDIA","name":"NVIDIA Corporation","url":"https://www.nvidia.com/"}],"numbering":{"title":{"offset":1}},"source_url":"https://github.com/projectpythia/api-cookbook/blob/main/notebooks/example-workflows/cneos-fireball.ipynb","edit_url":"https://github.com/projectpythia/api-cookbook/edit/main/notebooks/example-workflows/cneos-fireball.ipynb","thumbnail":"/api-cookbook/build/22ccf97c98df98a0886e7227e136ac12.gif","exports":[{"format":"ipynb","filename":"cneos-fireball.ipynb","url":"/api-cookbook/build/cneos-fireball-2e60912a3343ed1007d574b88edb190d.ipynb"}]},"widgets":{},"mdast":{"type":"root","children":[{"type":"block","kind":"notebook-content","children":[{"type":"paragraph","position":{"start":{"line":1,"column":1},"end":{"line":1,"column":1}},"children":[{"type":"image","url":"/api-cookbook/build/22ccf97c98df98a0886e7227e136ac12.gif","alt":"Bay Area Fireball","key":"ow3QQWiUSU","urlSource":"https://www.nasa.gov/wp-content/uploads/2023/03/704419main_meteor-gif-full_full.gif?w=1041"}],"key":"Ob2DuuwYd3"},{"type":"paragraph","position":{"start":{"line":3,"column":1},"end":{"line":3,"column":1}},"children":[{"type":"link","url":"https://www.nasa.gov/image-article/bay-area-fireball-oct-17-2012/","position":{"start":{"line":3,"column":1},"end":{"line":3,"column":1}},"children":[{"type":"text","value":"Bay Area Fireball, October 17, 2012","position":{"start":{"line":3,"column":1},"end":{"line":3,"column":1}},"key":"mmEw6gHE4W"}],"urlSource":"https://www.nasa.gov/image-article/bay-area-fireball-oct-17-2012/","key":"MYCNsJNEQQ"}],"key":"CySendZ9K8"}],"key":"NZRwuESpLX"},{"type":"block","kind":"notebook-content","children":[{"type":"heading","depth":1,"position":{"start":{"line":1,"column":1},"end":{"line":1,"column":1}},"children":[{"type":"text","value":"NASA API: World Map of Fireball Impacts","position":{"start":{"line":1,"column":1},"end":{"line":1,"column":1}},"key":"I9HwZeHTbB"}],"identifier":"nasa-api-world-map-of-fireball-impacts","label":"NASA API: World Map of Fireball Impacts","html_id":"nasa-api-world-map-of-fireball-impacts","implicit":true,"key":"UCaYT261KV"}],"key":"edMRh1QkCp"},{"type":"block","kind":"notebook-content","children":[{"type":"thematicBreak","position":{"start":{"line":1,"column":1},"end":{"line":1,"column":1}},"key":"QeMxv1wkCJ"}],"key":"BsNEIkjNBf"},{"type":"block","kind":"notebook-content","children":[{"type":"heading","depth":2,"position":{"start":{"line":1,"column":1},"end":{"line":1,"column":1}},"children":[{"type":"text","value":"Overview","position":{"start":{"line":1,"column":1},"end":{"line":1,"column":1}},"key":"IhuNDDIEBq"}],"identifier":"overview","label":"Overview","html_id":"overview","implicit":true,"key":"BC21F64ixZ"},{"type":"paragraph","position":{"start":{"line":2,"column":1},"end":{"line":2,"column":1}},"children":[{"type":"text","value":"This notebook will cover all the steps to access bright meteor and fireball impact data collected by NASA’s CNEOS and produce a global plot of impact sites","position":{"start":{"line":2,"column":1},"end":{"line":2,"column":1}},"key":"W4Z1RZqZeI"}],"key":"DbF4hz8kyj"},{"type":"list","ordered":true,"start":1,"spread":false,"position":{"start":{"line":4,"column":1},"end":{"line":9,"column":1}},"children":[{"type":"listItem","spread":true,"position":{"start":{"line":4,"column":1},"end":{"line":4,"column":1}},"children":[{"type":"paragraph","children":[{"type":"text","value":"Prerequisites","position":{"start":{"line":4,"column":1},"end":{"line":4,"column":1}},"key":"rBF54qOLbZ"}],"key":"KU6P48QdcT"}],"key":"zTaaXx4xOP"},{"type":"listItem","spread":true,"position":{"start":{"line":5,"column":1},"end":{"line":5,"column":1}},"children":[{"type":"paragraph","children":[{"type":"text","value":"CNEOS Overview","position":{"start":{"line":5,"column":1},"end":{"line":5,"column":1}},"key":"pQ8fTUag55"}],"key":"JscOLxqrMT"}],"key":"papRpw8RQ6"},{"type":"listItem","spread":true,"position":{"start":{"line":6,"column":1},"end":{"line":6,"column":1}},"children":[{"type":"paragraph","children":[{"type":"text","value":"Imports","position":{"start":{"line":6,"column":1},"end":{"line":6,"column":1}},"key":"H83jhdbOY8"}],"key":"LtouBTzpkh"}],"key":"TSkn8dSgb4"},{"type":"listItem","spread":true,"position":{"start":{"line":7,"column":1},"end":{"line":7,"column":1}},"children":[{"type":"paragraph","children":[{"type":"text","value":"Access and Organize Data","position":{"start":{"line":7,"column":1},"end":{"line":7,"column":1}},"key":"cK7sUEfmhk"}],"key":"eDORAzTLHi"}],"key":"L5oPPAZdCJ"},{"type":"listItem","spread":true,"position":{"start":{"line":8,"column":1},"end":{"line":8,"column":1}},"children":[{"type":"paragraph","children":[{"type":"text","value":"Plot Earth Fireball Impacts","position":{"start":{"line":8,"column":1},"end":{"line":8,"column":1}},"key":"wodzbCoiJ1"}],"key":"ZLlm2Y57k3"}],"key":"SjImhx0maK"},{"type":"listItem","spread":true,"position":{"start":{"line":9,"column":1},"end":{"line":9,"column":1}},"children":[{"type":"paragraph","children":[{"type":"text","value":"Summary","position":{"start":{"line":9,"column":1},"end":{"line":9,"column":1}},"key":"aBvtvVpYxD"}],"key":"gpD7p9MHIz"}],"key":"vL6vHjZwdC"}],"key":"IoLf5ZFZpu"}],"key":"RkJoYgkZuV"},{"type":"block","kind":"notebook-content","children":[{"type":"heading","depth":2,"position":{"start":{"line":1,"column":1},"end":{"line":1,"column":1}},"children":[{"type":"text","value":"Prerequisites","position":{"start":{"line":1,"column":1},"end":{"line":1,"column":1}},"key":"MgnMhfeqJr"}],"identifier":"prerequisites","label":"Prerequisites","html_id":"prerequisites","implicit":true,"key":"FmdIoCsPaC"},{"type":"table","position":{"start":{"line":2,"column":1},"end":{"line":6,"column":1}},"children":[{"type":"tableRow","position":{"start":{"line":2,"column":1},"end":{"line":2,"column":1}},"children":[{"type":"tableCell","header":true,"position":{"start":{"line":2,"column":1},"end":{"line":2,"column":1}},"children":[{"type":"text","value":"Concepts","position":{"start":{"line":2,"column":1},"end":{"line":2,"column":1}},"key":"tP6E87wo4z"}],"key":"FeROlYN1KD"},{"type":"tableCell","header":true,"position":{"start":{"line":2,"column":1},"end":{"line":2,"column":1}},"children":[{"type":"text","value":"Importance","position":{"start":{"line":2,"column":1},"end":{"line":2,"column":1}},"key":"bldOxzIrkX"}],"key":"iPtcxY9q0W"},{"type":"tableCell","header":true,"position":{"start":{"line":2,"column":1},"end":{"line":2,"column":1}},"children":[{"type":"text","value":"Notes","position":{"start":{"line":2,"column":1},"end":{"line":2,"column":1}},"key":"fHdpliIw1d"}],"key":"uLVoLONYXa"}],"key":"S9GrfuiGeS"},{"type":"tableRow","position":{"start":{"line":4,"column":1},"end":{"line":4,"column":1}},"children":[{"type":"tableCell","position":{"start":{"line":4,"column":1},"end":{"line":4,"column":1}},"children":[{"type":"link","url":"https://foundations.projectpythia.org/core/matplotlib/matplotlib-basics","position":{"start":{"line":4,"column":1},"end":{"line":4,"column":1}},"children":[{"type":"text","value":"Intro to Matplotlib","position":{"start":{"line":4,"column":1},"end":{"line":4,"column":1}},"key":"va7cf8IMoG"}],"urlSource":"https://foundations.projectpythia.org/core/matplotlib/matplotlib-basics","key":"SN0PmxDfn7"}],"key":"HUodFlN0ux"},{"type":"tableCell","position":{"start":{"line":4,"column":1},"end":{"line":4,"column":1}},"children":[{"type":"text","value":"Necessary","position":{"start":{"line":4,"column":1},"end":{"line":4,"column":1}},"key":"J9z0PS0BSg"}],"key":"n3Pc8yi7Dh"},{"type":"tableCell","position":{"start":{"line":4,"column":1},"end":{"line":4,"column":1}},"children":[{"type":"text","value":"Plotting on a data","position":{"start":{"line":4,"column":1},"end":{"line":4,"column":1}},"key":"EKC0rX7gYA"}],"key":"C1ZUKp5jR2"}],"key":"TziFNo8eiy"},{"type":"tableRow","position":{"start":{"line":5,"column":1},"end":{"line":5,"column":1}},"children":[{"type":"tableCell","position":{"start":{"line":5,"column":1},"end":{"line":5,"column":1}},"children":[{"type":"link","url":"https://geopandas.org/en/stable/","position":{"start":{"line":5,"column":1},"end":{"line":5,"column":1}},"children":[{"type":"text","value":"Intro to GeoPandas","position":{"start":{"line":5,"column":1},"end":{"line":5,"column":1}},"key":"XI7bQxaiBj"}],"urlSource":"https://geopandas.org/en/stable/","key":"qRJbUfCJwr"}],"key":"gDHvX8Y3cX"},{"type":"tableCell","position":{"start":{"line":5,"column":1},"end":{"line":5,"column":1}},"children":[{"type":"text","value":"Necessary","position":{"start":{"line":5,"column":1},"end":{"line":5,"column":1}},"key":"xfPuFvZIXv"}],"key":"ujDqN86HfG"},{"type":"tableCell","position":{"start":{"line":5,"column":1},"end":{"line":5,"column":1}},"children":[{"type":"text","value":"Plotting on a world map","position":{"start":{"line":5,"column":1},"end":{"line":5,"column":1}},"key":"vgE6bojxoB"}],"key":"SOC4B8Rwzj"}],"key":"cDuoYcMNgJ"},{"type":"tableRow","position":{"start":{"line":6,"column":1},"end":{"line":6,"column":1}},"children":[{"type":"tableCell","position":{"start":{"line":6,"column":1},"end":{"line":6,"column":1}},"children":[{"type":"link","url":"https://foundations.projectpythia.org/core/pandas/pandas","position":{"start":{"line":6,"column":1},"end":{"line":6,"column":1}},"children":[{"type":"text","value":"Intro to Pandas","position":{"start":{"line":6,"column":1},"end":{"line":6,"column":1}},"key":"bWqvvKja81"}],"urlSource":"https://foundations.projectpythia.org/core/pandas/pandas","key":"hgxRNmUHyY"}],"key":"OROakn5CCx"},{"type":"tableCell","position":{"start":{"line":6,"column":1},"end":{"line":6,"column":1}},"children":[{"type":"text","value":"Necessary","position":{"start":{"line":6,"column":1},"end":{"line":6,"column":1}},"key":"pBk3xA5mw8"}],"key":"tSNTadOg7d"},{"type":"tableCell","position":{"start":{"line":6,"column":1},"end":{"line":6,"column":1}},"children":[{"type":"text","value":"Familiarity with working with dataframes","position":{"start":{"line":6,"column":1},"end":{"line":6,"column":1}},"key":"BqST2FFvlL"}],"key":"FZFCdY6DTy"}],"key":"ToI5LzRsEj"}],"key":"aFcoYs83RC"}],"key":"V06GNITcDy"},{"type":"block","kind":"notebook-content","children":[{"type":"thematicBreak","position":{"start":{"line":1,"column":1},"end":{"line":1,"column":1}},"key":"eB02jVjbXT"}],"key":"H8TVWDBHIR"},{"type":"block","kind":"notebook-content","children":[{"type":"heading","depth":2,"position":{"start":{"line":1,"column":1},"end":{"line":1,"column":1}},"children":[{"type":"text","value":"CNEOS Overivew","position":{"start":{"line":1,"column":1},"end":{"line":1,"column":1}},"key":"r00kN4hqdB"}],"identifier":"cneos-overivew","label":"CNEOS Overivew","html_id":"cneos-overivew","implicit":true,"key":"DaRjIv9qiB"}],"key":"YKezHaqQsl"},{"type":"block","kind":"notebook-content","children":[{"type":"paragraph","position":{"start":{"line":1,"column":1},"end":{"line":1,"column":1}},"children":[{"type":"text","value":"A shooting star is a common term for a meteor and form bright trails of light that are often bright enough to be visible during the day. A “fireball” is a term for expectionally bright meteor that enters the Earth’s atmosphere at high speeds. A meteor that form fireballs can be over one meter long. A “bolide” typically refers to a fireball that breaks up in the atmosphere. These objects are tracked by the ","position":{"start":{"line":1,"column":1},"end":{"line":1,"column":1}},"key":"fzMl4EcDjX"},{"type":"link","url":"https://cneos.jpl.nasa.gov/","position":{"start":{"line":1,"column":1},"end":{"line":1,"column":1}},"children":[{"type":"text","value":"Center for Near Earth Object Studies (CNEOS)","position":{"start":{"line":1,"column":1},"end":{"line":1,"column":1}},"key":"DebrremW5H"}],"urlSource":"https://cneos.jpl.nasa.gov/","key":"V52WHYs6a6"},{"type":"text","value":" and information about the Peak Brightness, Velocity, and Joules of energy radiatated can be retrieved from CNEOS via an API","position":{"start":{"line":1,"column":1},"end":{"line":1,"column":1}},"key":"F689AXiXlZ"}],"key":"xGyh7q7zt1"}],"key":"EXUxWZfmFY"},{"type":"block","kind":"notebook-content","children":[{"type":"heading","depth":3,"position":{"start":{"line":1,"column":1},"end":{"line":1,"column":1}},"children":[{"type":"text","value":"Fireball Data API","position":{"start":{"line":1,"column":1},"end":{"line":1,"column":1}},"key":"WUIyvWACOw"}],"identifier":"fireball-data-api","label":"Fireball Data API","html_id":"fireball-data-api","implicit":true,"key":"o6qBqRFjjE"}],"key":"qpi5kQ4R8e"},{"type":"block","kind":"notebook-content","children":[{"type":"paragraph","position":{"start":{"line":1,"column":1},"end":{"line":1,"column":1}},"children":[{"type":"text","value":"This notebook will query the Fireball API for data from the last decade of observations","position":{"start":{"line":1,"column":1},"end":{"line":1,"column":1}},"key":"BzFapJwY6p"}],"key":"oky7n9ZC7B"},{"type":"paragraph","position":{"start":{"line":3,"column":1},"end":{"line":3,"column":1}},"children":[{"type":"text","value":"JPL’s Center for Near-Earth Objects Studies ","position":{"start":{"line":3,"column":1},"end":{"line":3,"column":1}},"key":"jB1tYdgoWk"},{"type":"link","url":"https://ssd-api.jpl.nasa.gov/doc/fireball.html","position":{"start":{"line":3,"column":1},"end":{"line":3,"column":1}},"children":[{"type":"text","value":"API “Fireball”","position":{"start":{"line":3,"column":1},"end":{"line":3,"column":1}},"key":"hBH6em2DC1"}],"urlSource":"https://ssd-api.jpl.nasa.gov/doc/fireball.html","key":"XSjkvLIceJ"},{"type":"text","value":" is an API that will return machine-readable data in the form of a JSON.","position":{"start":{"line":3,"column":1},"end":{"line":3,"column":1}},"key":"YUXxotBJQd"}],"key":"E6Yt5lKUMy"},{"type":"paragraph","position":{"start":{"line":5,"column":1},"end":{"line":5,"column":1}},"children":[{"type":"text","value":"All queries to the Fireball Data API make requests to ","position":{"start":{"line":5,"column":1},"end":{"line":5,"column":1}},"key":"HjnDx0Ho2P"},{"type":"inlineCode","value":"https://ssd-api.jpl.nasa.gov/fireball.api","position":{"start":{"line":5,"column":1},"end":{"line":5,"column":1}},"key":"Quo49ipqqt"}],"key":"ehZOCA9fgu"},{"type":"paragraph","position":{"start":{"line":7,"column":1},"end":{"line":7,"column":1}},"children":[{"type":"text","value":"The API accepts different query parameters to filter the data","position":{"start":{"line":7,"column":1},"end":{"line":7,"column":1}},"key":"DTRKhSrwvB"}],"key":"L0vnmKzjxL"},{"type":"paragraph","position":{"start":{"line":9,"column":1},"end":{"line":9,"column":1}},"children":[{"type":"text","value":"Directly querying ","position":{"start":{"line":9,"column":1},"end":{"line":9,"column":1}},"key":"cf48cLO6FD"},{"type":"inlineCode","value":"https://ssd-api.jpl.nasa.gov/fireball.api","position":{"start":{"line":9,"column":1},"end":{"line":9,"column":1}},"key":"QPJ1AOLqRc"},{"type":"text","value":" will return all the data of fireball impacts in reverse-chronological order","position":{"start":{"line":9,"column":1},"end":{"line":9,"column":1}},"key":"SWX1groPXF"}],"key":"vVA2KSQtyX"},{"type":"table","position":{"start":{"line":11,"column":1},"end":{"line":26,"column":1}},"children":[{"type":"tableRow","position":{"start":{"line":11,"column":1},"end":{"line":11,"column":1}},"children":[{"type":"tableCell","header":true,"position":{"start":{"line":11,"column":1},"end":{"line":11,"column":1}},"children":[{"type":"text","value":"Parameter","position":{"start":{"line":11,"column":1},"end":{"line":11,"column":1}},"key":"cebZ9WdweU"}],"key":"x0Zgs2XHqp"},{"type":"tableCell","header":true,"position":{"start":{"line":11,"column":1},"end":{"line":11,"column":1}},"children":[{"type":"text","value":"Type","position":{"start":{"line":11,"column":1},"end":{"line":11,"column":1}},"key":"EXrLfyuISA"}],"key":"AQZEabcXo2"},{"type":"tableCell","header":true,"position":{"start":{"line":11,"column":1},"end":{"line":11,"column":1}},"children":[{"type":"text","value":"Description","position":{"start":{"line":11,"column":1},"end":{"line":11,"column":1}},"key":"GbVXiCy0yL"}],"key":"hRNyF2pF71"}],"key":"h6wGrOSIDB"},{"type":"tableRow","position":{"start":{"line":13,"column":1},"end":{"line":13,"column":1}},"children":[{"type":"tableCell","position":{"start":{"line":13,"column":1},"end":{"line":13,"column":1}},"children":[{"type":"text","value":"date-min","position":{"start":{"line":13,"column":1},"end":{"line":13,"column":1}},"key":"qdPbeiflnL"}],"key":"am3liAAk8q"},{"type":"tableCell","position":{"start":{"line":13,"column":1},"end":{"line":13,"column":1}},"children":[{"type":"text","value":"string","position":{"start":{"line":13,"column":1},"end":{"line":13,"column":1}},"key":"FOGFiKztbA"}],"key":"ET9IBaGHix"},{"type":"tableCell","position":{"start":{"line":13,"column":1},"end":{"line":13,"column":1}},"children":[{"type":"text","value":"exclude data earlier than this date ","position":{"start":{"line":13,"column":1},"end":{"line":13,"column":1}},"key":"qUOITn8ECq"},{"type":"inlineCode","value":"YYYY-MM-DD","position":{"start":{"line":13,"column":1},"end":{"line":13,"column":1}},"key":"lmAoCLAeQM"},{"type":"text","value":" or date/time ","position":{"start":{"line":13,"column":1},"end":{"line":13,"column":1}},"key":"rjHvGm87hb"},{"type":"inlineCode","value":"YYYY-MM-DDThh:mm:ss","position":{"start":{"line":13,"column":1},"end":{"line":13,"column":1}},"key":"GnukEabck1"}],"key":"KY582jlLPA"}],"key":"Z5J6ReRjMj"},{"type":"tableRow","position":{"start":{"line":14,"column":1},"end":{"line":14,"column":1}},"children":[{"type":"tableCell","position":{"start":{"line":14,"column":1},"end":{"line":14,"column":1}},"children":[{"type":"text","value":"date-max","position":{"start":{"line":14,"column":1},"end":{"line":14,"column":1}},"key":"FqERwjY7bP"}],"key":"NTyJTAxvY5"},{"type":"tableCell","position":{"start":{"line":14,"column":1},"end":{"line":14,"column":1}},"children":[{"type":"text","value":"string","position":{"start":{"line":14,"column":1},"end":{"line":14,"column":1}},"key":"NhCBMwnZfv"}],"key":"NohaIHhBZB"},{"type":"tableCell","position":{"start":{"line":14,"column":1},"end":{"line":14,"column":1}},"children":[{"type":"text","value":"exclude data later than this date ","position":{"start":{"line":14,"column":1},"end":{"line":14,"column":1}},"key":"nKjfeK0GNH"},{"type":"inlineCode","value":"YYYY-MM-DD","position":{"start":{"line":14,"column":1},"end":{"line":14,"column":1}},"key":"Yk5wYPMYoW"},{"type":"text","value":" or date/time ","position":{"start":{"line":14,"column":1},"end":{"line":14,"column":1}},"key":"JHVkZG2MON"},{"type":"inlineCode","value":"YYYY-MM-DDThh:mm:ss","position":{"start":{"line":14,"column":1},"end":{"line":14,"column":1}},"key":"rl6iy7ZZ8f"}],"key":"ymLM5rldZn"}],"key":"vNbhdKGIae"},{"type":"tableRow","position":{"start":{"line":15,"column":1},"end":{"line":15,"column":1}},"children":[{"type":"tableCell","position":{"start":{"line":15,"column":1},"end":{"line":15,"column":1}},"children":[{"type":"text","value":"energy-min","position":{"start":{"line":15,"column":1},"end":{"line":15,"column":1}},"key":"Dhy5hm8umW"}],"key":"wiblnvZ7fw"},{"type":"tableCell","position":{"start":{"line":15,"column":1},"end":{"line":15,"column":1}},"children":[{"type":"text","value":"string","position":{"start":{"line":15,"column":1},"end":{"line":15,"column":1}},"key":"YJ0obSHgRy"}],"key":"jTEf4d00N6"},{"type":"tableCell","position":{"start":{"line":15,"column":1},"end":{"line":15,"column":1}},"children":[{"type":"text","value":"exclude data with total-radiated-energy less than this positive value in joules ×1010 (e.g., ","position":{"start":{"line":15,"column":1},"end":{"line":15,"column":1}},"key":"Tu3liRBRa3"},{"type":"inlineCode","value":"0.3","position":{"start":{"line":15,"column":1},"end":{"line":15,"column":1}},"key":"TcqR6vHCQh"},{"type":"text","value":" = 0.3×1010 joules)","position":{"start":{"line":15,"column":1},"end":{"line":15,"column":1}},"key":"WYrdFJP7Do"}],"key":"pqg1FQGtiM"}],"key":"sLEec8z9RB"},{"type":"tableRow","position":{"start":{"line":16,"column":1},"end":{"line":16,"column":1}},"children":[{"type":"tableCell","position":{"start":{"line":16,"column":1},"end":{"line":16,"column":1}},"children":[{"type":"text","value":"energy-max","position":{"start":{"line":16,"column":1},"end":{"line":16,"column":1}},"key":"iQrIyZZhYd"}],"key":"nvHW4c7Npr"},{"type":"tableCell","position":{"start":{"line":16,"column":1},"end":{"line":16,"column":1}},"children":[{"type":"text","value":"string","position":{"start":{"line":16,"column":1},"end":{"line":16,"column":1}},"key":"XHSuXo6vhk"}],"key":"F6GhySDSOa"},{"type":"tableCell","position":{"start":{"line":16,"column":1},"end":{"line":16,"column":1}},"children":[{"type":"text","value":"exclude data with total-radiated-energy greater than this (see energy-min)","position":{"start":{"line":16,"column":1},"end":{"line":16,"column":1}},"key":"GL9QG6mbZN"}],"key":"uN0MUDh7bm"}],"key":"He3wZXeXKU"},{"type":"tableRow","position":{"start":{"line":17,"column":1},"end":{"line":17,"column":1}},"children":[{"type":"tableCell","position":{"start":{"line":17,"column":1},"end":{"line":17,"column":1}},"children":[{"type":"text","value":"impact-e-min","position":{"start":{"line":17,"column":1},"end":{"line":17,"column":1}},"key":"jUwcInLv2u"}],"key":"AsLWjG5eb5"},{"type":"tableCell","position":{"start":{"line":17,"column":1},"end":{"line":17,"column":1}},"children":[{"type":"text","value":"string","position":{"start":{"line":17,"column":1},"end":{"line":17,"column":1}},"key":"rqQfTxIfD0"}],"key":"lwcqwKu5yI"},{"type":"tableCell","position":{"start":{"line":17,"column":1},"end":{"line":17,"column":1}},"children":[{"type":"text","value":"exclude data with estimated impact energy less than this positive value in kilotons (kt) (e.g., ","position":{"start":{"line":17,"column":1},"end":{"line":17,"column":1}},"key":"tLbvPC4m7H"},{"type":"inlineCode","value":"0.08","position":{"start":{"line":17,"column":1},"end":{"line":17,"column":1}},"key":"Suht9ZSkG2"},{"type":"text","value":" kt)","position":{"start":{"line":17,"column":1},"end":{"line":17,"column":1}},"key":"xrA8OQ4OGT"}],"key":"RNP5mki67p"}],"key":"KTCw8aGbZY"},{"type":"tableRow","position":{"start":{"line":18,"column":1},"end":{"line":18,"column":1}},"children":[{"type":"tableCell","position":{"start":{"line":18,"column":1},"end":{"line":18,"column":1}},"children":[{"type":"text","value":"impact-e-max","position":{"start":{"line":18,"column":1},"end":{"line":18,"column":1}},"key":"gQBloHGD90"}],"key":"JpnCsm5omi"},{"type":"tableCell","position":{"start":{"line":18,"column":1},"end":{"line":18,"column":1}},"children":[{"type":"text","value":"string","position":{"start":{"line":18,"column":1},"end":{"line":18,"column":1}},"key":"uypzeyAYQs"}],"key":"sj1mbGuKAO"},{"type":"tableCell","position":{"start":{"line":18,"column":1},"end":{"line":18,"column":1}},"children":[{"type":"text","value":"exclude data with total-radiated-energy greater than this (see impact-e-min)","position":{"start":{"line":18,"column":1},"end":{"line":18,"column":1}},"key":"cZn3gyR5E0"}],"key":"W3XOkU9DXv"}],"key":"Gxkc227H2s"},{"type":"tableRow","position":{"start":{"line":19,"column":1},"end":{"line":19,"column":1}},"children":[{"type":"tableCell","position":{"start":{"line":19,"column":1},"end":{"line":19,"column":1}},"children":[{"type":"text","value":"alt-min","position":{"start":{"line":19,"column":1},"end":{"line":19,"column":1}},"key":"dyPHfjeNeX"}],"key":"AoACTKsz4c"},{"type":"tableCell","position":{"start":{"line":19,"column":1},"end":{"line":19,"column":1}},"children":[{"type":"text","value":"number","position":{"start":{"line":19,"column":1},"end":{"line":19,"column":1}},"key":"sBvgawqlzk"}],"key":"BIewve75W3"},{"type":"tableCell","position":{"start":{"line":19,"column":1},"end":{"line":19,"column":1}},"children":[{"type":"text","value":"exclude data from objects with an altitude less than this (e.g., ","position":{"start":{"line":19,"column":1},"end":{"line":19,"column":1}},"key":"MzaPDeO6zP"},{"type":"inlineCode","value":"22","position":{"start":{"line":19,"column":1},"end":{"line":19,"column":1}},"key":"RjbOuQKlb8"},{"type":"text","value":" meaning objects smaller than this)","position":{"start":{"line":19,"column":1},"end":{"line":19,"column":1}},"key":"AWzZFk1L3u"}],"key":"XEleCILhDK"}],"key":"hzgOz9zuQx"},{"type":"tableRow","position":{"start":{"line":20,"column":1},"end":{"line":20,"column":1}},"children":[{"type":"tableCell","position":{"start":{"line":20,"column":1},"end":{"line":20,"column":1}},"children":[{"type":"text","value":"alt-max","position":{"start":{"line":20,"column":1},"end":{"line":20,"column":1}},"key":"rBmFwni1RY"}],"key":"u0EiuBwqr9"},{"type":"tableCell","position":{"start":{"line":20,"column":1},"end":{"line":20,"column":1}},"children":[{"type":"text","value":"number","position":{"start":{"line":20,"column":1},"end":{"line":20,"column":1}},"key":"B7MmGssLyz"}],"key":"rvK6bRegZN"},{"type":"tableCell","position":{"start":{"line":20,"column":1},"end":{"line":20,"column":1}},"children":[{"type":"text","value":"exclude data from objects with an altitude greater than this (e.g., ","position":{"start":{"line":20,"column":1},"end":{"line":20,"column":1}},"key":"ttxfgzjnyW"},{"type":"inlineCode","value":"17.75","position":{"start":{"line":20,"column":1},"end":{"line":20,"column":1}},"key":"gYMD0GfGWX"},{"type":"text","value":" meaning objects larger than this)","position":{"start":{"line":20,"column":1},"end":{"line":20,"column":1}},"key":"bS9l1gE1uM"}],"key":"eMz2Wg68L2"}],"key":"HbAZljtfR3"},{"type":"tableRow","position":{"start":{"line":21,"column":1},"end":{"line":21,"column":1}},"children":[{"type":"tableCell","position":{"start":{"line":21,"column":1},"end":{"line":21,"column":1}},"children":[{"type":"text","value":"req-loc","position":{"start":{"line":21,"column":1},"end":{"line":21,"column":1}},"key":"rMiLNHWHu1"}],"key":"PMg9L5rcvG"},{"type":"tableCell","position":{"start":{"line":21,"column":1},"end":{"line":21,"column":1}},"children":[{"type":"text","value":"boolean","position":{"start":{"line":21,"column":1},"end":{"line":21,"column":1}},"key":"e1IUm58xGz"}],"key":"elOAyxPYEL"},{"type":"tableCell","position":{"start":{"line":21,"column":1},"end":{"line":21,"column":1}},"children":[{"type":"text","value":"location (latitude and longitude) required; when set ","position":{"start":{"line":21,"column":1},"end":{"line":21,"column":1}},"key":"JCjtSRuBo0"},{"type":"inlineCode","value":"true","position":{"start":{"line":21,"column":1},"end":{"line":21,"column":1}},"key":"jBCFwbcxtX"},{"type":"text","value":", exclude data without a location","position":{"start":{"line":21,"column":1},"end":{"line":21,"column":1}},"key":"GCZhVwxIN4"}],"key":"BK3xkdQncC"}],"key":"bCfhs6p3zm"},{"type":"tableRow","position":{"start":{"line":22,"column":1},"end":{"line":22,"column":1}},"children":[{"type":"tableCell","position":{"start":{"line":22,"column":1},"end":{"line":22,"column":1}},"children":[{"type":"text","value":"req-alt","position":{"start":{"line":22,"column":1},"end":{"line":22,"column":1}},"key":"K7j5adxitA"}],"key":"t2FIfOGPgZ"},{"type":"tableCell","position":{"start":{"line":22,"column":1},"end":{"line":22,"column":1}},"children":[{"type":"text","value":"boolean","position":{"start":{"line":22,"column":1},"end":{"line":22,"column":1}},"key":"vAzIqORNN8"}],"key":"zWQsVyzku7"},{"type":"tableCell","position":{"start":{"line":22,"column":1},"end":{"line":22,"column":1}},"children":[{"type":"text","value":"altitude required; when set ","position":{"start":{"line":22,"column":1},"end":{"line":22,"column":1}},"key":"rrWLhymHCL"},{"type":"inlineCode","value":"true","position":{"start":{"line":22,"column":1},"end":{"line":22,"column":1}},"key":"KKXd4CsNgo"},{"type":"text","value":", exclude data without an altitude","position":{"start":{"line":22,"column":1},"end":{"line":22,"column":1}},"key":"s2WM7KiY6Z"}],"key":"WvnVwFlsqW"}],"key":"JFCPLCgHHB"},{"type":"tableRow","position":{"start":{"line":23,"column":1},"end":{"line":23,"column":1}},"children":[{"type":"tableCell","position":{"start":{"line":23,"column":1},"end":{"line":23,"column":1}},"children":[{"type":"text","value":"req-vel-comp","position":{"start":{"line":23,"column":1},"end":{"line":23,"column":1}},"key":"ZXx9Tpy59o"}],"key":"a9Fl0HGBfj"},{"type":"tableCell","position":{"start":{"line":23,"column":1},"end":{"line":23,"column":1}},"children":[{"type":"text","value":"boolean","position":{"start":{"line":23,"column":1},"end":{"line":23,"column":1}},"key":"lqUdqzf1U8"}],"key":"Ig6E2orGEe"},{"type":"tableCell","position":{"start":{"line":23,"column":1},"end":{"line":23,"column":1}},"children":[{"type":"text","value":"pre-entry velocity components required; when set ","position":{"start":{"line":23,"column":1},"end":{"line":23,"column":1}},"key":"MvWlK6add0"},{"type":"inlineCode","value":"true","position":{"start":{"line":23,"column":1},"end":{"line":23,"column":1}},"key":"VyQYTIPh1T"},{"type":"text","value":", exclude data without pre-entry velocity components","position":{"start":{"line":23,"column":1},"end":{"line":23,"column":1}},"key":"yiP4tV07U8"}],"key":"b3yIS4LsMC"}],"key":"AgaZhRn3q0"},{"type":"tableRow","position":{"start":{"line":24,"column":1},"end":{"line":24,"column":1}},"children":[{"type":"tableCell","position":{"start":{"line":24,"column":1},"end":{"line":24,"column":1}},"children":[{"type":"text","value":"vel-comp","position":{"start":{"line":24,"column":1},"end":{"line":24,"column":1}},"key":"yrTdqrKJWt"}],"key":"L2XwFZ6wD4"},{"type":"tableCell","position":{"start":{"line":24,"column":1},"end":{"line":24,"column":1}},"children":[{"type":"text","value":"boolean","position":{"start":{"line":24,"column":1},"end":{"line":24,"column":1}},"key":"nFxBdY49aM"}],"key":"MiFPRhhOqO"},{"type":"tableCell","position":{"start":{"line":24,"column":1},"end":{"line":24,"column":1}},"children":[{"type":"text","value":"include pre-entry velocity components","position":{"start":{"line":24,"column":1},"end":{"line":24,"column":1}},"key":"eFj0cyb7in"}],"key":"k8u3yzf0Ra"}],"key":"bE4oBxLiDE"},{"type":"tableRow","position":{"start":{"line":25,"column":1},"end":{"line":25,"column":1}},"children":[{"type":"tableCell","position":{"start":{"line":25,"column":1},"end":{"line":25,"column":1}},"children":[{"type":"text","value":"sort","position":{"start":{"line":25,"column":1},"end":{"line":25,"column":1}},"key":"fQy8QbYXaq"}],"key":"yt4jFzUKIM"},{"type":"tableCell","position":{"start":{"line":25,"column":1},"end":{"line":25,"column":1}},"children":[{"type":"text","value":"string","position":{"start":{"line":25,"column":1},"end":{"line":25,"column":1}},"key":"n3sxpp0MsO"}],"key":"vsY2ILqkrm"},{"type":"tableCell","position":{"start":{"line":25,"column":1},"end":{"line":25,"column":1}},"children":[{"type":"text","value":"sort data on the specified field: “date”, “energy”, “impact-e”, “vel”, or “alt” (default sort order is ascending: prepend “-“ for descending)","position":{"start":{"line":25,"column":1},"end":{"line":25,"column":1}},"key":"BzMS8mPRkZ"}],"key":"c17y9Wvu2C"}],"key":"H17WBGDtZM"},{"type":"tableRow","position":{"start":{"line":26,"column":1},"end":{"line":26,"column":1}},"children":[{"type":"tableCell","position":{"start":{"line":26,"column":1},"end":{"line":26,"column":1}},"children":[{"type":"text","value":"limit","position":{"start":{"line":26,"column":1},"end":{"line":26,"column":1}},"key":"XyCJb4Aaak"}],"key":"EnPAOzE9WX"},{"type":"tableCell","position":{"start":{"line":26,"column":1},"end":{"line":26,"column":1}},"children":[{"type":"text","value":"number","position":{"start":{"line":26,"column":1},"end":{"line":26,"column":1}},"key":"oDdmosZcQ0"}],"key":"dc7UxTFd22"},{"type":"tableCell","position":{"start":{"line":26,"column":1},"end":{"line":26,"column":1}},"children":[{"type":"text","value":"limit data to the first N results (where N is the specified number and must be an integer value greater than zero)","position":{"start":{"line":26,"column":1},"end":{"line":26,"column":1}},"key":"vzt02ySbXp"}],"key":"Q27qbqQEbt"}],"key":"n6pYMnvEOT"}],"key":"INIevH4whj"},{"type":"paragraph","position":{"start":{"line":28,"column":1},"end":{"line":28,"column":1}},"children":[{"type":"text","value":"Results from API will be returned as JSON with a number of fields","position":{"start":{"line":28,"column":1},"end":{"line":28,"column":1}},"key":"yWurRLzLTF"}],"key":"gU73aQZTQl"},{"type":"table","position":{"start":{"line":30,"column":1},"end":{"line":42,"column":1}},"children":[{"type":"tableRow","position":{"start":{"line":30,"column":1},"end":{"line":30,"column":1}},"children":[{"type":"tableCell","header":true,"position":{"start":{"line":30,"column":1},"end":{"line":30,"column":1}},"children":[{"type":"text","value":"Field","position":{"start":{"line":30,"column":1},"end":{"line":30,"column":1}},"key":"lFLjuSORGi"}],"key":"iNmk14pQjY"},{"type":"tableCell","header":true,"position":{"start":{"line":30,"column":1},"end":{"line":30,"column":1}},"children":[{"type":"text","value":"Description","position":{"start":{"line":30,"column":1},"end":{"line":30,"column":1}},"key":"D29GOVl4NK"}],"key":"H3EpX5RFa5"}],"key":"H9FqwxBQBQ"},{"type":"tableRow","position":{"start":{"line":32,"column":1},"end":{"line":32,"column":1}},"children":[{"type":"tableCell","position":{"start":{"line":32,"column":1},"end":{"line":32,"column":1}},"children":[{"type":"text","value":"date","position":{"start":{"line":32,"column":1},"end":{"line":32,"column":1}},"key":"KU0FssTzMU"}],"key":"KNsrUedQAp"},{"type":"tableCell","position":{"start":{"line":32,"column":1},"end":{"line":32,"column":1}},"children":[{"type":"text","value":"date/time of peak brightness (GMT)","position":{"start":{"line":32,"column":1},"end":{"line":32,"column":1}},"key":"FGZOi4kXRQ"}],"key":"CbEnCRZSSx"}],"key":"Z382SebpOD"},{"type":"tableRow","position":{"start":{"line":33,"column":1},"end":{"line":33,"column":1}},"children":[{"type":"tableCell","position":{"start":{"line":33,"column":1},"end":{"line":33,"column":1}},"children":[{"type":"text","value":"lat","position":{"start":{"line":33,"column":1},"end":{"line":33,"column":1}},"key":"pUMu74kuJ9"}],"key":"rqBT9WdPlZ"},{"type":"tableCell","position":{"start":{"line":33,"column":1},"end":{"line":33,"column":1}},"children":[{"type":"text","value":"latitude at peak brightness (degrees)","position":{"start":{"line":33,"column":1},"end":{"line":33,"column":1}},"key":"GG0MN5YusZ"}],"key":"TJSgxEReZ3"}],"key":"CPKxogoEWN"},{"type":"tableRow","position":{"start":{"line":34,"column":1},"end":{"line":34,"column":1}},"children":[{"type":"tableCell","position":{"start":{"line":34,"column":1},"end":{"line":34,"column":1}},"children":[{"type":"text","value":"lon","position":{"start":{"line":34,"column":1},"end":{"line":34,"column":1}},"key":"TEK5ycGuDy"}],"key":"yxV6O0iTA0"},{"type":"tableCell","position":{"start":{"line":34,"column":1},"end":{"line":34,"column":1}},"children":[{"type":"text","value":"longitude at peak brightness (degrees)","position":{"start":{"line":34,"column":1},"end":{"line":34,"column":1}},"key":"SsvurTXPRP"}],"key":"tIfvNVYFQy"}],"key":"wiDaPgVta4"},{"type":"tableRow","position":{"start":{"line":35,"column":1},"end":{"line":35,"column":1}},"children":[{"type":"tableCell","position":{"start":{"line":35,"column":1},"end":{"line":35,"column":1}},"children":[{"type":"text","value":"lat-dir","position":{"start":{"line":35,"column":1},"end":{"line":35,"column":1}},"key":"wbLQ3K4vMS"}],"key":"ou9R0FnGLk"},{"type":"tableCell","position":{"start":{"line":35,"column":1},"end":{"line":35,"column":1}},"children":[{"type":"text","value":"latitude direction (“N” or “S”)","position":{"start":{"line":35,"column":1},"end":{"line":35,"column":1}},"key":"SlEtgCBPtF"}],"key":"Lsjfyu0PZF"}],"key":"IgMZt8cvYR"},{"type":"tableRow","position":{"start":{"line":36,"column":1},"end":{"line":36,"column":1}},"children":[{"type":"tableCell","position":{"start":{"line":36,"column":1},"end":{"line":36,"column":1}},"children":[{"type":"text","value":"lon-dir","position":{"start":{"line":36,"column":1},"end":{"line":36,"column":1}},"key":"IZIcq1PPbb"}],"key":"iaoCWOZNks"},{"type":"tableCell","position":{"start":{"line":36,"column":1},"end":{"line":36,"column":1}},"children":[{"type":"text","value":"latitude direction (“E” or “W”)","position":{"start":{"line":36,"column":1},"end":{"line":36,"column":1}},"key":"dTbvGBSm8y"}],"key":"EkGetgJ586"}],"key":"BZ3x54mTZP"},{"type":"tableRow","position":{"start":{"line":37,"column":1},"end":{"line":37,"column":1}},"children":[{"type":"tableCell","position":{"start":{"line":37,"column":1},"end":{"line":37,"column":1}},"children":[{"type":"text","value":"alt","position":{"start":{"line":37,"column":1},"end":{"line":37,"column":1}},"key":"i27zleGcjF"}],"key":"E4uc7moO1j"},{"type":"tableCell","position":{"start":{"line":37,"column":1},"end":{"line":37,"column":1}},"children":[{"type":"text","value":"altitude above the geoid at peak brightness (km)","position":{"start":{"line":37,"column":1},"end":{"line":37,"column":1}},"key":"ZXn2flt58Y"}],"key":"WzlrqDyL9l"}],"key":"wF1YLchm1A"},{"type":"tableRow","position":{"start":{"line":38,"column":1},"end":{"line":38,"column":1}},"children":[{"type":"tableCell","position":{"start":{"line":38,"column":1},"end":{"line":38,"column":1}},"children":[{"type":"text","value":"energy","position":{"start":{"line":38,"column":1},"end":{"line":38,"column":1}},"key":"qiYIJjtexc"}],"key":"VDlgTn1RRf"},{"type":"tableCell","position":{"start":{"line":38,"column":1},"end":{"line":38,"column":1}},"children":[{"type":"text","value":"approximate total radiated energy (10^10 joules)","position":{"start":{"line":38,"column":1},"end":{"line":38,"column":1}},"key":"MiKEN5jgWE"}],"key":"lf48DAOsK2"}],"key":"rk22s1viuZ"},{"type":"tableRow","position":{"start":{"line":39,"column":1},"end":{"line":39,"column":1}},"children":[{"type":"tableCell","position":{"start":{"line":39,"column":1},"end":{"line":39,"column":1}},"children":[{"type":"text","value":"impact-e","position":{"start":{"line":39,"column":1},"end":{"line":39,"column":1}},"key":"VFQxPUBoLF"}],"key":"P3FEWp3Um8"},{"type":"tableCell","position":{"start":{"line":39,"column":1},"end":{"line":39,"column":1}},"children":[{"type":"text","value":"approximate total impact energy (kt)","position":{"start":{"line":39,"column":1},"end":{"line":39,"column":1}},"key":"CowJaIKJiu"}],"key":"wKI40i72Qj"}],"key":"WYe3vAzfmC"},{"type":"tableRow","position":{"start":{"line":40,"column":1},"end":{"line":40,"column":1}},"children":[{"type":"tableCell","position":{"start":{"line":40,"column":1},"end":{"line":40,"column":1}},"children":[{"type":"text","value":"vx","position":{"start":{"line":40,"column":1},"end":{"line":40,"column":1}},"key":"gAnhtWdwbf"}],"key":"o64rlFjUxZ"},{"type":"tableCell","position":{"start":{"line":40,"column":1},"end":{"line":40,"column":1}},"children":[{"type":"text","value":"pre-entry velocity (Earth centered X component, km/s)","position":{"start":{"line":40,"column":1},"end":{"line":40,"column":1}},"key":"Rj1UDrrmTk"}],"key":"XXvLEmcNtg"}],"key":"rVsbvAV7xa"},{"type":"tableRow","position":{"start":{"line":41,"column":1},"end":{"line":41,"column":1}},"children":[{"type":"tableCell","position":{"start":{"line":41,"column":1},"end":{"line":41,"column":1}},"children":[{"type":"text","value":"vy","position":{"start":{"line":41,"column":1},"end":{"line":41,"column":1}},"key":"MBZA8HOM8H"}],"key":"IMxIg7zPxN"},{"type":"tableCell","position":{"start":{"line":41,"column":1},"end":{"line":41,"column":1}},"children":[{"type":"text","value":"pre-entry velocity (Earth centered Y component, km/s)","position":{"start":{"line":41,"column":1},"end":{"line":41,"column":1}},"key":"ktNG9VZLvN"}],"key":"tosb9NkqCD"}],"key":"hx5l0ZUQTY"},{"type":"tableRow","position":{"start":{"line":42,"column":1},"end":{"line":42,"column":1}},"children":[{"type":"tableCell","position":{"start":{"line":42,"column":1},"end":{"line":42,"column":1}},"children":[{"type":"text","value":"vz","position":{"start":{"line":42,"column":1},"end":{"line":42,"column":1}},"key":"dUttBvAwQW"}],"key":"AG9HU1v2iH"},{"type":"tableCell","position":{"start":{"line":42,"column":1},"end":{"line":42,"column":1}},"children":[{"type":"text","value":"pre-entry velocity (Earth centered Z component, km/s)","position":{"start":{"line":42,"column":1},"end":{"line":42,"column":1}},"key":"lATFb8A4At"}],"key":"lfVhuS7PJC"}],"key":"gWnhLIigWU"}],"key":"F8KCbPXZ6O"},{"type":"heading","depth":2,"position":{"start":{"line":44,"column":1},"end":{"line":44,"column":1}},"children":[{"type":"text","value":"Example JSON result","position":{"start":{"line":44,"column":1},"end":{"line":44,"column":1}},"key":"tDMNSkvUQT"}],"identifier":"example-json-result","label":"Example JSON result","html_id":"example-json-result","implicit":true,"key":"q97rimZaYO"},{"type":"paragraph","position":{"start":{"line":46,"column":1},"end":{"line":46,"column":1}},"children":[{"type":"text","value":"Return the last 3 records ","position":{"start":{"line":46,"column":1},"end":{"line":46,"column":1}},"key":"rHX3Qirr0a"},{"type":"inlineCode","value":"https://ssd-api.jpl.nasa.gov/fireball.api?limit=3","position":{"start":{"line":46,"column":1},"end":{"line":46,"column":1}},"key":"HlhgxDMC36"}],"key":"zi4xAMSK27"},{"type":"code","lang":"","value":"{\n    \"signature\":\n        {\n            \"version\":\"1.0\",\n            \"source\":\"NASA/JPL Fireball Data API\"\n        },\n    \"count\":\"3\",\n    \"fields\":[\"date\",\"energy\",\"impact-e\",\"lat\",\"lat-dir\",\"lon\",\"lon-dir\",\"alt\",\"vel\"],\n    \"data\":[\n        [\"2024-06-03 01:13:51\",\"2.6\",\"0.092\",\"63.1\",\"S\",\"53.2\",\"W\",\"60.0\",null],\n        [\"2024-06-01 23:24:59\",\"7.9\",\"0.25\",\"1.0\",\"S\",\"15.9\",\"W\",\"26.5\",\"12.6\"],\n        [\"2024-05-27 03:19:36\",\"8.4\",\"0.26\",\"1.7\",\"N\",\"39.4\",\"W\",\"56.0\",\"39.2\"]\n    ]\n}","position":{"start":{"line":48,"column":1},"end":{"line":63,"column":1}},"key":"fI99UswAsD"}],"key":"PMoxe5LhdK"},{"type":"block","kind":"notebook-content","children":[{"type":"heading","depth":2,"position":{"start":{"line":1,"column":1},"end":{"line":1,"column":1}},"children":[{"type":"text","value":"Imports","position":{"start":{"line":1,"column":1},"end":{"line":1,"column":1}},"key":"IXgafrIpJD"}],"identifier":"imports","label":"Imports","html_id":"imports","implicit":true,"key":"NUBJeJmeoy"}],"key":"cZ29NxDFIw"},{"type":"block","kind":"notebook-code","children":[{"type":"code","lang":"python","executable":true,"value":"import requests                 # submit API request query\nimport pandas as pd             # organizes data retrieved by the API\nimport geopandas                # generate a world map\nimport matplotlib.pyplot as plt # plotting data","key":"keRief4Mp8"},{"type":"output","id":"fnpmd4NIGQ5hLKWhPDB_q","data":[],"key":"quqNAeqXxg"}],"key":"IVopo8FUg2"},{"type":"block","kind":"notebook-content","children":[{"type":"heading","depth":2,"position":{"start":{"line":1,"column":1},"end":{"line":1,"column":1}},"children":[{"type":"text","value":"Request Fireball Data via API","position":{"start":{"line":1,"column":1},"end":{"line":1,"column":1}},"key":"cHkh5w5qaa"}],"identifier":"request-fireball-data-via-api","label":"Request Fireball Data via API","html_id":"request-fireball-data-via-api","implicit":true,"key":"GvVoXBMkhp"}],"key":"lno2jCsmhy"},{"type":"block","kind":"notebook-content","children":[{"type":"paragraph","position":{"start":{"line":1,"column":1},"end":{"line":1,"column":1}},"children":[{"type":"text","value":"To retrieve all the fireballs recorded in the last decade (2014-2024)","position":{"start":{"line":1,"column":1},"end":{"line":1,"column":1}},"key":"Wq3Xzd2nFI"}],"key":"qkjrl8PsWf"}],"key":"DEpQUwhew8"},{"type":"block","kind":"notebook-code","children":[{"type":"code","lang":"python","executable":true,"value":"data_since = \"2014-01-01\"\nlast_decade_fireball = requests.get(f\"https://ssd-api.jpl.nasa.gov/fireball.api?date-min={data_since}\")\nlast_decade_fireball.status_code # 200 is a valid request","key":"sktMeg5Has"},{"type":"output","id":"kPJ_79oY1Ob0itxD3xGlz","data":[{"output_type":"execute_result","execution_count":2,"metadata":{},"data":{"text/plain":{"content":"200","content_type":"text/plain"}}}],"key":"qdauUvA2sM"}],"key":"dkbMCD3OrZ"},{"type":"block","kind":"notebook-code","children":[{"type":"code","lang":"python","executable":true,"value":"fireball_json = last_decade_fireball.json()","key":"K3O1Pa8Swv"},{"type":"output","id":"DEgEGOmMVIoVK9F4vY4rg","data":[],"key":"f7iHqjBctf"}],"key":"bWAG7xc9w2"},{"type":"block","kind":"notebook-code","children":[{"type":"code","lang":"python","executable":true,"value":"# print out data labels\nprint(f\"fields = {fireball_json['fields']}\")","key":"W2pKTtQwaj"},{"type":"output","id":"GXOKSKpnH_DyVerdhYtIs","data":[{"output_type":"stream","name":"stdout","text":"fields = ['date', 'energy', 'impact-e', 'lat', 'lat-dir', 'lon', 'lon-dir', 'alt', 'vel']\n"}],"key":"EXjGtegQ31"}],"key":"yK86qAFhvX"},{"type":"block","kind":"notebook-code","children":[{"type":"code","lang":"python","executable":true,"value":"# convert JSON data to a Pandas dataframe\nfireball_df = pd.DataFrame(fireball_json[\"data\"], columns=fireball_json[\"fields\"])\nfireball_df","key":"su44Q66OZ7"},{"type":"output","id":"PPItqpbYpLWjl2goleaLY","data":[{"output_type":"execute_result","execution_count":5,"metadata":{},"data":{"text/plain":{"content":"                    date energy impact-e   lat lat-dir    lon lon-dir   alt  \\\n0    2025-11-15 00:48:43   10.5     0.32  62.2       S   94.7       W  30.0   \n1    2025-11-11 17:39:51    9.3     0.28  27.3       N   79.8       W  42.0   \n2    2025-10-20 13:31:27    2.0    0.073   5.7       N  135.2       W  41.0   \n3    2025-09-13 22:24:59   16.7     0.48  38.1       S   64.8       W  25.1   \n4    2025-09-10 11:00:57    2.8    0.098  14.8       S  142.4       W  37.0   \n..                   ...    ...      ...   ...     ...    ...     ...   ...   \n431  2014-02-13 06:47:41     63      1.5  13.3       N  110.7       W  25.0   \n432  2014-01-19 02:54:38     14     0.41  66.1       S   74.6       E  None   \n433  2014-01-15 02:46:13     14     0.41  18.5       S  141.8       E  29.6   \n434  2014-01-12 16:00:48    7.8     0.24   2.9       N   64.4       E  37.0   \n435  2014-01-08 17:05:33   3.82     0.13   1.2       S  147.1       E  18.7   \n\n      vel  \n0    16.0  \n1    18.7  \n2    26.7  \n3    17.8  \n4    None  \n..    ...  \n431  None  \n432  None  \n433  None  \n434  16.2  \n435  44.8  \n\n[436 rows x 9 columns]","content_type":"text/plain"},"text/html":{"content":"<div>\n<style scoped>\n    .dataframe tbody tr th:only-of-type {\n        vertical-align: middle;\n    }\n\n    .dataframe tbody tr th {\n        vertical-align: top;\n    }\n\n    .dataframe thead th {\n        text-align: right;\n    }\n</style>\n<table border=\"1\" class=\"dataframe\">\n  <thead>\n    <tr style=\"text-align: right;\">\n      <th></th>\n      <th>date</th>\n      <th>energy</th>\n      <th>impact-e</th>\n      <th>lat</th>\n      <th>lat-dir</th>\n      <th>lon</th>\n      <th>lon-dir</th>\n      <th>alt</th>\n      <th>vel</th>\n    </tr>\n  </thead>\n  <tbody>\n    <tr>\n      <th>0</th>\n      <td>2025-11-15 00:48:43</td>\n      <td>10.5</td>\n      <td>0.32</td>\n      <td>62.2</td>\n      <td>S</td>\n      <td>94.7</td>\n      <td>W</td>\n      <td>30.0</td>\n      <td>16.0</td>\n    </tr>\n    <tr>\n      <th>1</th>\n      <td>2025-11-11 17:39:51</td>\n      <td>9.3</td>\n      <td>0.28</td>\n      <td>27.3</td>\n      <td>N</td>\n      <td>79.8</td>\n      <td>W</td>\n      <td>42.0</td>\n      <td>18.7</td>\n    </tr>\n    <tr>\n      <th>2</th>\n      <td>2025-10-20 13:31:27</td>\n      <td>2.0</td>\n      <td>0.073</td>\n      <td>5.7</td>\n      <td>N</td>\n      <td>135.2</td>\n      <td>W</td>\n      <td>41.0</td>\n      <td>26.7</td>\n    </tr>\n    <tr>\n      <th>3</th>\n      <td>2025-09-13 22:24:59</td>\n      <td>16.7</td>\n      <td>0.48</td>\n      <td>38.1</td>\n      <td>S</td>\n      <td>64.8</td>\n      <td>W</td>\n      <td>25.1</td>\n      <td>17.8</td>\n    </tr>\n    <tr>\n      <th>4</th>\n      <td>2025-09-10 11:00:57</td>\n      <td>2.8</td>\n      <td>0.098</td>\n      <td>14.8</td>\n      <td>S</td>\n      <td>142.4</td>\n      <td>W</td>\n      <td>37.0</td>\n      <td>None</td>\n    </tr>\n    <tr>\n      <th>...</th>\n      <td>...</td>\n      <td>...</td>\n      <td>...</td>\n      <td>...</td>\n      <td>...</td>\n      <td>...</td>\n      <td>...</td>\n      <td>...</td>\n      <td>...</td>\n    </tr>\n    <tr>\n      <th>431</th>\n      <td>2014-02-13 06:47:41</td>\n      <td>63</td>\n      <td>1.5</td>\n      <td>13.3</td>\n      <td>N</td>\n      <td>110.7</td>\n      <td>W</td>\n      <td>25.0</td>\n      <td>None</td>\n    </tr>\n    <tr>\n      <th>432</th>\n      <td>2014-01-19 02:54:38</td>\n      <td>14</td>\n      <td>0.41</td>\n      <td>66.1</td>\n      <td>S</td>\n      <td>74.6</td>\n      <td>E</td>\n      <td>None</td>\n      <td>None</td>\n    </tr>\n    <tr>\n      <th>433</th>\n      <td>2014-01-15 02:46:13</td>\n      <td>14</td>\n      <td>0.41</td>\n      <td>18.5</td>\n      <td>S</td>\n      <td>141.8</td>\n      <td>E</td>\n      <td>29.6</td>\n      <td>None</td>\n    </tr>\n    <tr>\n      <th>434</th>\n      <td>2014-01-12 16:00:48</td>\n      <td>7.8</td>\n      <td>0.24</td>\n      <td>2.9</td>\n      <td>N</td>\n      <td>64.4</td>\n      <td>E</td>\n      <td>37.0</td>\n      <td>16.2</td>\n    </tr>\n    <tr>\n      <th>435</th>\n      <td>2014-01-08 17:05:33</td>\n      <td>3.82</td>\n      <td>0.13</td>\n      <td>1.2</td>\n      <td>S</td>\n      <td>147.1</td>\n      <td>E</td>\n      <td>18.7</td>\n      <td>44.8</td>\n    </tr>\n  </tbody>\n</table>\n<p>436 rows × 9 columns</p>\n</div>","content_type":"text/html"}}}],"key":"ahzRGMSoZo"}],"key":"nTH2ULJQFH"},{"type":"block","kind":"notebook-code","children":[{"type":"code","lang":"python","executable":true,"value":"# remove nan and duplicated data rows and reindex rows\nfireball_df.dropna(inplace=True, ignore_index=True)\n\n# convert columnss from strings to a float\nfireball_df[\"energy\"] = fireball_df[\"energy\"].astype(float)\nfireball_df[\"impact-e\"] = fireball_df[\"impact-e\"].astype(float)\nfireball_df[\"lat\"] = fireball_df[\"lat\"].astype(float)\nfireball_df[\"lon\"] = fireball_df[\"lon\"].astype(float)\nfireball_df[\"alt\"] = fireball_df[\"alt\"].astype(float)\nfireball_df[\"vel\"] = fireball_df[\"vel\"].astype(float)\n\n# convert latitude to negative if lat-dir is S and longitude to negative if lon-dir is W\nfireball_df['lat'] = fireball_df['lat'].mask(fireball_df['lat-dir'].eq('S'), -fireball_df['lat'])\nfireball_df['lon'] = fireball_df['lon'].mask(fireball_df['lon-dir'].eq('W'), -fireball_df['lon'])\n\n# rename columns\nfireball_df = fireball_df.rename(columns= {\"impact-e\": \"impact energy\",\n                                           \"lat\": \"latitude\",\n                                           \"lat-dir\": \"latitude direction\",\n                                           \"lon\": \"longitude\",\n                                           \"lon-dir\": \"longitude direction\",\n                                           \"alt\": \"altitude\",\n                                           \"vel\": \"velocity\"})\n\n\nfireball_df","key":"GBLyyGtfWo"},{"type":"output","id":"Fl2VcKRwL9_2lDP1O-zhl","data":[{"output_type":"execute_result","execution_count":6,"metadata":{},"data":{"text/plain":{"content":"                    date  energy  impact energy  latitude latitude direction  \\\n0    2025-11-15 00:48:43   10.50          0.320     -62.2                  S   \n1    2025-11-11 17:39:51    9.30          0.280      27.3                  N   \n2    2025-10-20 13:31:27    2.00          0.073       5.7                  N   \n3    2025-09-13 22:24:59   16.70          0.480     -38.1                  S   \n4    2025-09-09 17:49:10   15.30          0.440      -2.3                  S   \n..                   ...     ...            ...       ...                ...   \n253  2014-05-16 12:42:47   35.10          0.920     -44.2                  S   \n254  2014-05-08 19:42:37  105.00          2.400     -36.9                  S   \n255  2014-03-29 13:45:42    3.98          0.130     -28.7                  S   \n256  2014-01-12 16:00:48    7.80          0.240       2.9                  N   \n257  2014-01-08 17:05:33    3.82          0.130      -1.2                  S   \n\n     longitude longitude direction  altitude  velocity  \n0        -94.7                   W      30.0      16.0  \n1        -79.8                   W      42.0      18.7  \n2       -135.2                   W      41.0      26.7  \n3        -64.8                   W      25.1      17.8  \n4        -39.5                   W      24.0      20.7  \n..         ...                 ...       ...       ...  \n253     -176.2                   W      44.0      16.5  \n254       87.3                   E      35.4      19.0  \n255      121.5                   E      30.7      16.3  \n256       64.4                   E      37.0      16.2  \n257      147.1                   E      18.7      44.8  \n\n[258 rows x 9 columns]","content_type":"text/plain"},"text/html":{"content":"<div>\n<style scoped>\n    .dataframe tbody tr th:only-of-type {\n        vertical-align: middle;\n    }\n\n    .dataframe tbody tr th {\n        vertical-align: top;\n    }\n\n    .dataframe thead th {\n        text-align: right;\n    }\n</style>\n<table border=\"1\" class=\"dataframe\">\n  <thead>\n    <tr style=\"text-align: right;\">\n      <th></th>\n      <th>date</th>\n      <th>energy</th>\n      <th>impact energy</th>\n      <th>latitude</th>\n      <th>latitude direction</th>\n      <th>longitude</th>\n      <th>longitude direction</th>\n      <th>altitude</th>\n      <th>velocity</th>\n    </tr>\n  </thead>\n  <tbody>\n    <tr>\n      <th>0</th>\n      <td>2025-11-15 00:48:43</td>\n      <td>10.50</td>\n      <td>0.320</td>\n      <td>-62.2</td>\n      <td>S</td>\n      <td>-94.7</td>\n      <td>W</td>\n      <td>30.0</td>\n      <td>16.0</td>\n    </tr>\n    <tr>\n      <th>1</th>\n      <td>2025-11-11 17:39:51</td>\n      <td>9.30</td>\n      <td>0.280</td>\n      <td>27.3</td>\n      <td>N</td>\n      <td>-79.8</td>\n      <td>W</td>\n      <td>42.0</td>\n      <td>18.7</td>\n    </tr>\n    <tr>\n      <th>2</th>\n      <td>2025-10-20 13:31:27</td>\n      <td>2.00</td>\n      <td>0.073</td>\n      <td>5.7</td>\n      <td>N</td>\n      <td>-135.2</td>\n      <td>W</td>\n      <td>41.0</td>\n      <td>26.7</td>\n    </tr>\n    <tr>\n      <th>3</th>\n      <td>2025-09-13 22:24:59</td>\n      <td>16.70</td>\n      <td>0.480</td>\n      <td>-38.1</td>\n      <td>S</td>\n      <td>-64.8</td>\n      <td>W</td>\n      <td>25.1</td>\n      <td>17.8</td>\n    </tr>\n    <tr>\n      <th>4</th>\n      <td>2025-09-09 17:49:10</td>\n      <td>15.30</td>\n      <td>0.440</td>\n      <td>-2.3</td>\n      <td>S</td>\n      <td>-39.5</td>\n      <td>W</td>\n      <td>24.0</td>\n      <td>20.7</td>\n    </tr>\n    <tr>\n      <th>...</th>\n      <td>...</td>\n      <td>...</td>\n      <td>...</td>\n      <td>...</td>\n      <td>...</td>\n      <td>...</td>\n      <td>...</td>\n      <td>...</td>\n      <td>...</td>\n    </tr>\n    <tr>\n      <th>253</th>\n      <td>2014-05-16 12:42:47</td>\n      <td>35.10</td>\n      <td>0.920</td>\n      <td>-44.2</td>\n      <td>S</td>\n      <td>-176.2</td>\n      <td>W</td>\n      <td>44.0</td>\n      <td>16.5</td>\n    </tr>\n    <tr>\n      <th>254</th>\n      <td>2014-05-08 19:42:37</td>\n      <td>105.00</td>\n      <td>2.400</td>\n      <td>-36.9</td>\n      <td>S</td>\n      <td>87.3</td>\n      <td>E</td>\n      <td>35.4</td>\n      <td>19.0</td>\n    </tr>\n    <tr>\n      <th>255</th>\n      <td>2014-03-29 13:45:42</td>\n      <td>3.98</td>\n      <td>0.130</td>\n      <td>-28.7</td>\n      <td>S</td>\n      <td>121.5</td>\n      <td>E</td>\n      <td>30.7</td>\n      <td>16.3</td>\n    </tr>\n    <tr>\n      <th>256</th>\n      <td>2014-01-12 16:00:48</td>\n      <td>7.80</td>\n      <td>0.240</td>\n      <td>2.9</td>\n      <td>N</td>\n      <td>64.4</td>\n      <td>E</td>\n      <td>37.0</td>\n      <td>16.2</td>\n    </tr>\n    <tr>\n      <th>257</th>\n      <td>2014-01-08 17:05:33</td>\n      <td>3.82</td>\n      <td>0.130</td>\n      <td>-1.2</td>\n      <td>S</td>\n      <td>147.1</td>\n      <td>E</td>\n      <td>18.7</td>\n      <td>44.8</td>\n    </tr>\n  </tbody>\n</table>\n<p>258 rows × 9 columns</p>\n</div>","content_type":"text/html"}}}],"key":"E49cCXoYIV"}],"key":"PPUh9OXPjb"},{"type":"block","kind":"notebook-code","children":[{"type":"code","lang":"python","executable":true,"value":"fireball_df.info()","key":"p8UZipDUBy"},{"type":"output","id":"bk31UBx9USrdp5tf1stNJ","data":[{"output_type":"stream","name":"stdout","text":"<class 'pandas.core.frame.DataFrame'>\nRangeIndex: 258 entries, 0 to 257\nData columns (total 9 columns):\n #   Column               Non-Null Count  Dtype  \n---  ------               --------------  -----  \n 0   date                 258 non-null    object \n 1   energy               258 non-null    float64\n 2   impact energy        258 non-null    float64\n 3   latitude             258 non-null    float64\n 4   latitude direction   258 non-null    object \n 5   longitude            258 non-null    float64\n 6   longitude direction  258 non-null    object \n 7   altitude             258 non-null    float64\n 8   velocity             258 non-null    float64\ndtypes: float64(6), object(3)\nmemory usage: 18.3+ KB\n"}],"key":"JPUUtbItU6"}],"key":"bxuhxLAtGb"},{"type":"block","kind":"notebook-content","children":[{"type":"heading","depth":3,"position":{"start":{"line":1,"column":1},"end":{"line":1,"column":1}},"children":[{"type":"text","value":"Plot the Energy of Fireballs","position":{"start":{"line":1,"column":1},"end":{"line":1,"column":1}},"key":"NDqQGarvdr"}],"identifier":"plot-the-energy-of-fireballs","label":"Plot the Energy of Fireballs","html_id":"plot-the-energy-of-fireballs","implicit":true,"key":"e9hjxokoLF"}],"key":"EOF8WMItDO"},{"type":"block","kind":"notebook-code","children":[{"type":"code","lang":"python","executable":true,"value":"# retrieve world map from GeoPandas\nworld_map = geopandas.read_file(geopandas.datasets.get_path(\"naturalearth_lowres\"))\n\n# Set up world map plot\nfig, ax = plt.subplots(figsize=(15, 10))\nworld_map.plot(color=\"grey\", ax=ax)\n\n# Plot Fireball Locations with Energy\nx = fireball_df[\"longitude\"]\ny = fireball_df[\"latitude\"]\nz = fireball_df[\"energy\"]\nplt.scatter(x, y, s=5*z, c=z, cmap=\"autumn\")\nplt.colorbar(label=\"Approximate Total Radiated Energy (10^10 Joules)\")\n\n# Setup Axis Limits and Title/Labels\nplt.xlim([-180, 180])\nplt.ylim([-90, 90])\nplt.title(\"Energy of Fireball Observations\")\nplt.xlabel(\"Longitude (Degrees)\")\nplt.ylabel(\"Latitude (Degrees)\")\nplt.show()","key":"BYubmYvppp"},{"type":"output","id":"FcAynBW_8aCl3XryqbF-f","data":[{"output_type":"error","traceback":"\u001b[31m---------------------------------------------------------------------------\u001b[39m\n\u001b[31mAttributeError\u001b[39m                            Traceback (most recent call last)\n\u001b[36mCell\u001b[39m\u001b[36m \u001b[39m\u001b[32mIn[8]\u001b[39m\u001b[32m, line 2\u001b[39m\n\u001b[32m      1\u001b[39m \u001b[38;5;66;03m# retrieve world map from GeoPandas\u001b[39;00m\n\u001b[32m----> \u001b[39m\u001b[32m2\u001b[39m world_map = geopandas.read_file(\u001b[43mgeopandas\u001b[49m\u001b[43m.\u001b[49m\u001b[43mdatasets\u001b[49m\u001b[43m.\u001b[49m\u001b[43mget_path\u001b[49m\u001b[43m(\u001b[49m\u001b[33;43m\"\u001b[39;49m\u001b[33;43mnaturalearth_lowres\u001b[39;49m\u001b[33;43m\"\u001b[39;49m\u001b[43m)\u001b[49m)\n\u001b[32m      4\u001b[39m \u001b[38;5;66;03m# Set up world map plot\u001b[39;00m\n\u001b[32m      5\u001b[39m fig, ax = plt.subplots(figsize=(\u001b[32m15\u001b[39m, \u001b[32m10\u001b[39m))\n\n\u001b[36mFile \u001b[39m\u001b[32m~/micromamba/envs/api-cookbook-dev/lib/python3.14/site-packages/geopandas/datasets/__init__.py:18\u001b[39m, in \u001b[36mget_path\u001b[39m\u001b[34m(dataset)\u001b[39m\n\u001b[32m     12\u001b[39m error_msg = (\n\u001b[32m     13\u001b[39m     \u001b[33m\"\u001b[39m\u001b[33mThe geopandas.dataset has been deprecated and was removed in GeoPandas \u001b[39m\u001b[33m\"\u001b[39m\n\u001b[32m     14\u001b[39m     \u001b[33mf\u001b[39m\u001b[33m\"\u001b[39m\u001b[33m1.0. You can get the original \u001b[39m\u001b[33m'\u001b[39m\u001b[38;5;132;01m{\u001b[39;00mdataset\u001b[38;5;132;01m}\u001b[39;00m\u001b[33m'\u001b[39m\u001b[33m data from \u001b[39m\u001b[33m\"\u001b[39m\n\u001b[32m     15\u001b[39m     \u001b[33mf\u001b[39m\u001b[33m\"\u001b[39m\u001b[38;5;132;01m{\u001b[39;00mne_message\u001b[38;5;250m \u001b[39m\u001b[38;5;28;01mif\u001b[39;00m\u001b[38;5;250m \u001b[39m\u001b[33m'\u001b[39m\u001b[33mnatural\u001b[39m\u001b[33m'\u001b[39m\u001b[38;5;250m \u001b[39m\u001b[38;5;129;01min\u001b[39;00m\u001b[38;5;250m \u001b[39mdataset\u001b[38;5;250m \u001b[39m\u001b[38;5;28;01melse\u001b[39;00m\u001b[38;5;250m \u001b[39mnybb_message\u001b[38;5;132;01m}\u001b[39;00m\u001b[33m\"\u001b[39m\n\u001b[32m     16\u001b[39m )\n\u001b[32m     17\u001b[39m \u001b[38;5;28;01mif\u001b[39;00m dataset \u001b[38;5;129;01min\u001b[39;00m _prev_available:\n\u001b[32m---> \u001b[39m\u001b[32m18\u001b[39m     \u001b[38;5;28;01mraise\u001b[39;00m \u001b[38;5;167;01mAttributeError\u001b[39;00m(error_msg)\n\u001b[32m     19\u001b[39m \u001b[38;5;28;01melse\u001b[39;00m:\n\u001b[32m     20\u001b[39m     error_msg = (\n\u001b[32m     21\u001b[39m         \u001b[33m\"\u001b[39m\u001b[33mThe geopandas.dataset has been deprecated and \u001b[39m\u001b[33m\"\u001b[39m\n\u001b[32m     22\u001b[39m         \u001b[33m\"\u001b[39m\u001b[33mwas removed in GeoPandas 1.0. New sample datasets are now available \u001b[39m\u001b[33m\"\u001b[39m\n\u001b[32m     23\u001b[39m         \u001b[33m\"\u001b[39m\u001b[33min the geodatasets package (https://geodatasets.readthedocs.io/en/latest/)\u001b[39m\u001b[33m\"\u001b[39m\n\u001b[32m     24\u001b[39m     )\n\n\u001b[31mAttributeError\u001b[39m: The geopandas.dataset has been deprecated and was removed in GeoPandas 1.0. You can get the original 'naturalearth_lowres' data from https://www.naturalearthdata.com/downloads/110m-cultural-vectors/.","ename":"AttributeError","evalue":"The geopandas.dataset has been deprecated and was removed in GeoPandas 1.0. You can get the original 'naturalearth_lowres' data from https://www.naturalearthdata.com/downloads/110m-cultural-vectors/."}],"key":"Fo1rcEHMvy"}],"key":"CpmTYAcBgS"},{"type":"block","kind":"notebook-content","children":[{"type":"heading","depth":3,"position":{"start":{"line":1,"column":1},"end":{"line":1,"column":1}},"children":[{"type":"text","value":"Plot the Impact Energy of Fireballs","position":{"start":{"line":1,"column":1},"end":{"line":1,"column":1}},"key":"LWgup97yuZ"}],"identifier":"plot-the-impact-energy-of-fireballs","label":"Plot the Impact Energy of Fireballs","html_id":"plot-the-impact-energy-of-fireballs","implicit":true,"key":"U2QpNp2vRn"}],"key":"fFPFUL4qdW"},{"type":"block","kind":"notebook-code","children":[{"type":"code","lang":"python","executable":true,"value":"# retrieve world map from GeoPandas\nworld_map = geopandas.read_file(geopandas.datasets.get_path(\"naturalearth_lowres\"))\n\n# Set up world map plot\nfig, ax = plt.subplots(figsize=(15, 10))\nworld_map.plot(color=\"grey\", ax=ax)\n\n# Plot Fireball Locations with Energy\nx = fireball_df[\"longitude\"]\ny = fireball_df[\"latitude\"]\nz = fireball_df[\"impact energy\"]\nplt.scatter(x, y, s=5*z, c=z, cmap=\"autumn\")\nplt.colorbar(label=\"Approximate Total Impact Energy (kt)\")\n\n# Setup Axis Limits and Title/Labels\nplt.xlim([-180, 180])\nplt.ylim([-90, 90])\nplt.title(\"Total Impact Energy of Fireball Observations\")\nplt.xlabel(\"Longitude (Degrees)\")\nplt.ylabel(\"Latitude (Degrees)\")\nplt.show()","key":"BY9y3bnsYV"},{"type":"output","id":"JUvbwv3Wt-73DNa_9Waev","data":[],"key":"lGHz3yWolx"}],"key":"wo7m9XL3mL"},{"type":"block","kind":"notebook-content","children":[{"type":"heading","depth":3,"position":{"start":{"line":1,"column":1},"end":{"line":1,"column":1}},"children":[{"type":"text","value":"Plot the Velocity of Fireballs","position":{"start":{"line":1,"column":1},"end":{"line":1,"column":1}},"key":"tNvbWhaKqe"}],"identifier":"plot-the-velocity-of-fireballs","label":"Plot the Velocity of Fireballs","html_id":"plot-the-velocity-of-fireballs","implicit":true,"key":"m64MNz2tSk"}],"key":"b5yGlS7UtU"},{"type":"block","kind":"notebook-code","children":[{"type":"code","lang":"python","executable":true,"value":"# retrieve world map from GeoPandas\nworld_map = geopandas.read_file(geopandas.datasets.get_path(\"naturalearth_lowres\"))\n\n# Set up world map plot\nfig, ax = plt.subplots(figsize=(15, 10))\nworld_map.plot(color=\"grey\", ax=ax)\n\n# Plot Fireball Locations with Velocity\nx = fireball_df[\"longitude\"]\ny = fireball_df[\"latitude\"]\nz = fireball_df[\"velocity\"]\nplt.scatter(x, y, s=5*z, c=z, cmap=\"winter\")\nplt.colorbar(label=\"Pre-Entry Velocity (km/s)\")\n\n# Setup Axis Limits and Title/Labels\nplt.xlim([-180, 180])\nplt.ylim([-90, 90])\nplt.title(\"Pre-Entry Velocity of Fireball Observations\")\nplt.xlabel(\"Longitude (Degrees)\")\nplt.ylabel(\"Latitude (Degrees)\")\nplt.show()","key":"c2eVhnzDhJ"},{"type":"output","id":"8bGg0Dollv4G8ZKnQJRJ9","data":[],"key":"shFrqk4R5X"}],"key":"NC4TqaIJo0"},{"type":"block","kind":"notebook-content","children":[{"type":"heading","depth":3,"position":{"start":{"line":1,"column":1},"end":{"line":1,"column":1}},"children":[{"type":"text","value":"Plot the Altitude of Fireballs","position":{"start":{"line":1,"column":1},"end":{"line":1,"column":1}},"key":"Uj4Oq8UqDW"}],"identifier":"plot-the-altitude-of-fireballs","label":"Plot the Altitude of Fireballs","html_id":"plot-the-altitude-of-fireballs","implicit":true,"key":"dLpbHGKliv"}],"key":"SugvqjMvYf"},{"type":"block","kind":"notebook-code","children":[{"type":"code","lang":"python","executable":true,"value":"# retrieve world map from GeoPandas\nworld_map = geopandas.read_file(geopandas.datasets.get_path(\"naturalearth_lowres\"))\n\n# Set up world map plot\nfig, ax = plt.subplots(figsize=(15, 10))\nworld_map.plot(color=\"grey\", ax=ax)\n\n# Plot Fireball Locations with Energy\nx = fireball_df[\"longitude\"]\ny = fireball_df[\"latitude\"]\nz = fireball_df[\"altitude\"]\nplt.scatter(x, y, s=5*z, c=z, cmap=\"bone\")\nplt.colorbar(label=\"Altitude Above Geoid at Peak Brightness (km)\")\n\n# Setup Axis Limits and Title/Labels\nplt.xlim([-180, 180])\nplt.ylim([-90, 90])\nplt.title(\"Altitude of Fireball Observations\")\nplt.xlabel(\"Longitude (Degrees)\")\nplt.ylabel(\"Latitude (Degrees)\")\nplt.show()","key":"wBQftgy2ae"},{"type":"output","id":"N3XUNFWRhbTKgarOjTbMo","data":[],"key":"oMfrmkt60I"}],"key":"CqjCKiixVh"},{"type":"block","kind":"notebook-content","children":[{"type":"heading","depth":2,"position":{"start":{"line":1,"column":1},"end":{"line":1,"column":1}},"children":[{"type":"text","value":"Last Section","position":{"start":{"line":1,"column":1},"end":{"line":1,"column":1}},"key":"C4IxCC8zYD"}],"identifier":"last-section","label":"Last Section","html_id":"last-section","implicit":true,"key":"FNarzT09rR"},{"type":"paragraph","position":{"start":{"line":3,"column":1},"end":{"line":3,"column":1}},"children":[{"type":"text","value":"If you’re comfortable, and as we briefly used for our embedded logo up top, you can embed raw html into Jupyter Markdown cells (edit to see):","position":{"start":{"line":3,"column":1},"end":{"line":3,"column":1}},"key":"GS2LbCx8uG"}],"key":"hmfp8uYCAO"}],"key":"Ao632cdxaZ"},{"type":"block","kind":"notebook-content","children":[{"type":"div","class":"admonition alert alert-info","children":[{"type":"paragraph","children":[{"type":"text","value":"Info","key":"slipUfcFWn"}],"key":"htCVu47mwt"},{"type":"text","value":"Your relevant information here!","key":"ciLUmgB3Mp"}],"key":"MtVkS8cwYm"}],"key":"Rcqn4Ydv5n"},{"type":"block","kind":"notebook-content","children":[{"type":"paragraph","position":{"start":{"line":1,"column":1},"end":{"line":1,"column":1}},"children":[{"type":"text","value":"Feel free to copy this around and edit or play around with yourself. Some other ","position":{"start":{"line":1,"column":1},"end":{"line":1,"column":1}},"key":"rOE03JSW79"},{"type":"inlineCode","value":"admonitions","position":{"start":{"line":1,"column":1},"end":{"line":1,"column":1}},"key":"XnvOovMlDF"},{"type":"text","value":" you can put in:","position":{"start":{"line":1,"column":1},"end":{"line":1,"column":1}},"key":"f6hXnyOr5V"}],"key":"xKqj6mcg6Z"}],"key":"ysnU5Pl4ag"},{"type":"block","kind":"notebook-content","children":[{"type":"div","class":"admonition alert alert-success","children":[{"type":"paragraph","children":[{"type":"text","value":"Success","key":"JYAwSDRIXm"}],"key":"d4jaULRCmP"},{"type":"text","value":"We got this done after all!","key":"IHTh0INuQD"}],"key":"pAo6RvalVp"}],"key":"n9OhBXDo7d"},{"type":"block","kind":"notebook-content","children":[{"type":"div","class":"admonition alert alert-warning","children":[{"type":"paragraph","children":[{"type":"text","value":"Warning","key":"XP9CnzRrV8"}],"key":"jDMnfzp0v1"},{"type":"text","value":"Be careful!","key":"cLUtUMeBx8"}],"key":"WqnCg7QHXb"}],"key":"O3F2NayW1H"},{"type":"block","kind":"notebook-content","children":[{"type":"div","class":"admonition alert alert-danger","children":[{"type":"paragraph","children":[{"type":"text","value":"Danger","key":"xd0EZ00KB2"}],"key":"eBrQYJ7qUl"},{"type":"text","value":"Scary stuff be here.","key":"KfqATRAnFG"}],"key":"BTGfiQJ0dS"}],"key":"XZogA6pxot"},{"type":"block","kind":"notebook-content","children":[{"type":"paragraph","position":{"start":{"line":1,"column":1},"end":{"line":1,"column":1}},"children":[{"type":"text","value":"We also suggest checking out Jupyter Book’s ","position":{"start":{"line":1,"column":1},"end":{"line":1,"column":1}},"key":"KtQ3qp5k1h"},{"type":"link","url":"https://jupyterbook.org/content/metadata.html#jupyter-cell-tags","position":{"start":{"line":1,"column":1},"end":{"line":1,"column":1}},"children":[{"type":"text","value":"brief demonstration","position":{"start":{"line":1,"column":1},"end":{"line":1,"column":1}},"key":"jZj9SC7odF"}],"urlSource":"https://jupyterbook.org/content/metadata.html#jupyter-cell-tags","key":"EAUKFQRUGO"},{"type":"text","value":" on adding cell tags to your cells in Jupyter Notebook, Lab, or manually. Using these cell tags can allow you to ","position":{"start":{"line":1,"column":1},"end":{"line":1,"column":1}},"key":"PvCBsJNJsL"},{"type":"link","url":"https://jupyterbook.org/interactive/hiding.html","position":{"start":{"line":1,"column":1},"end":{"line":1,"column":1}},"children":[{"type":"text","value":"customize","position":{"start":{"line":1,"column":1},"end":{"line":1,"column":1}},"key":"jLjlo7km83"}],"urlSource":"https://jupyterbook.org/interactive/hiding.html","key":"eqd0unPowd"},{"type":"text","value":" how your code content is displayed and even ","position":{"start":{"line":1,"column":1},"end":{"line":1,"column":1}},"key":"H8onahslpF"},{"type":"link","url":"https://jupyterbook.org/content/execute.html#dealing-with-code-that-raises-errors","position":{"start":{"line":1,"column":1},"end":{"line":1,"column":1}},"children":[{"type":"text","value":"demonstrate errors","position":{"start":{"line":1,"column":1},"end":{"line":1,"column":1}},"key":"tDOyVGZJVF"}],"urlSource":"https://jupyterbook.org/content/execute.html#dealing-with-code-that-raises-errors","key":"SD87UK3RRq"},{"type":"text","value":" without altogether crashing our loyal army of machines!","position":{"start":{"line":1,"column":1},"end":{"line":1,"column":1}},"key":"CkMZqF0JSJ"}],"key":"Vd8LA1dAdQ"}],"key":"B61yNywlKD"},{"type":"block","kind":"notebook-content","children":[{"type":"thematicBreak","position":{"start":{"line":1,"column":1},"end":{"line":1,"column":1}},"key":"E9DaiJjbN6"}],"key":"sPDxlLLhYv"},{"type":"block","kind":"notebook-content","children":[{"type":"heading","depth":2,"position":{"start":{"line":1,"column":1},"end":{"line":1,"column":1}},"children":[{"type":"text","value":"Summary","position":{"start":{"line":1,"column":1},"end":{"line":1,"column":1}},"key":"Kn9Zsf9Ezl"}],"identifier":"summary","label":"Summary","html_id":"summary","implicit":true,"key":"P8ojH7NiLm"},{"type":"paragraph","position":{"start":{"line":2,"column":1},"end":{"line":2,"column":1}},"children":[{"type":"text","value":"Add one final ","position":{"start":{"line":2,"column":1},"end":{"line":2,"column":1}},"key":"rvnF6s5EOO"},{"type":"inlineCode","value":"---","position":{"start":{"line":2,"column":1},"end":{"line":2,"column":1}},"key":"EKNhZrK0Ou"},{"type":"text","value":" marking the end of your body of content, and then conclude with a brief single paragraph summarizing at a high level the key pieces that were learned and how they tied to your objectives. Look to reiterate what the most important takeaways were.","position":{"start":{"line":2,"column":1},"end":{"line":2,"column":1}},"key":"S8n0LkC6j4"}],"key":"hbwKhy2m9e"},{"type":"heading","depth":3,"position":{"start":{"line":4,"column":1},"end":{"line":4,"column":1}},"children":[{"type":"text","value":"What’s next?","position":{"start":{"line":4,"column":1},"end":{"line":4,"column":1}},"key":"kax2tmI9N0"}],"identifier":"whats-next","label":"What’s next?","html_id":"whats-next","implicit":true,"key":"qDzpdR8gbX"},{"type":"paragraph","position":{"start":{"line":5,"column":1},"end":{"line":5,"column":1}},"children":[{"type":"text","value":"Let Jupyter book tie this to the next (sequential) piece of content that people could move on to down below and in the sidebar. However, if this page uniquely enables your reader to tackle other nonsequential concepts throughout this book, or even external content, link to it here!","position":{"start":{"line":5,"column":1},"end":{"line":5,"column":1}},"key":"fKOx4q5Qc6"}],"key":"g72Pu0ThBs"}],"key":"CeEXLPPP9t"},{"type":"block","kind":"notebook-content","children":[{"type":"heading","depth":2,"position":{"start":{"line":1,"column":1},"end":{"line":1,"column":1}},"children":[{"type":"text","value":"Resources and references","position":{"start":{"line":1,"column":1},"end":{"line":1,"column":1}},"key":"HgboKo3Ryk"}],"identifier":"resources-and-references","label":"Resources and references","html_id":"resources-and-references","implicit":true,"key":"bkw70OJ9Xm"},{"type":"list","ordered":false,"spread":false,"position":{"start":{"line":3,"column":1},"end":{"line":3,"column":1}},"children":[{"type":"listItem","spread":true,"position":{"start":{"line":3,"column":1},"end":{"line":3,"column":1}},"children":[{"type":"paragraph","children":[{"type":"text","value":"More information about ","position":{"start":{"line":3,"column":1},"end":{"line":3,"column":1}},"key":"Psz9eulhp5"},{"type":"link","url":"https://medium.com/@kavee625/plotting-data-on-the-world-map-with-geopandas-f03742615196","position":{"start":{"line":3,"column":1},"end":{"line":3,"column":1}},"children":[{"type":"text","value":"plotting a world map with GeoPandas","position":{"start":{"line":3,"column":1},"end":{"line":3,"column":1}},"key":"bvNvNXjL0C"}],"urlSource":"https://medium.com/@kavee625/plotting-data-on-the-world-map-with-geopandas-f03742615196","key":"yo4g5Stbjx"}],"key":"XtANEmH1CS"}],"key":"Qwnpb8LHG4"}],"key":"BcZtt2nHvd"}],"key":"RyKqlhrRB9"}],"key":"rK2fJ32U9G"},"references":{"cite":{"order":[],"data":{}}},"footer":{"navigation":{"prev":{"title":"Visualizing Data with EPA’s Air Quality System (AQS) API","url":"/notebooks/example-workflows/air-quality-system-api","group":"Example Workflows"},"next":{"title":"Data access via earthaccess library and vizualization with cartopy","url":"/notebooks/example-workflows/earthaccess-sla-sss","group":"Example Workflows"}}},"domain":"http://localhost:3000"}